streamlit_html_sidebar/__init__.py
streamlit_html_sidebar/sidebar.py
streamlit_html_sidebar/static/sidebar.css
streamlit_html_sidebar/static/sidebar.js
streamlit_html_sidebar-0.2.0.dist-info/licenses/LICENSE
streamlit_html_sidebar-0.2.0.dist-info/METADATA
streamlit_html_sidebar-0.2.0.dist-info/WHEEL
streamlit_html_sidebar-0.2.0.dist-info/top_level.txt
streamlit_html_sidebar-0.2.0.dist-info/RECORD
